psql_chat/__init__.py
psql_chat/config.py
psql_chat/context7.py
psql_chat/database.py
psql_chat/llm.py
psql_chat/main.py
psql_chat/py.typed
psql_chat/rich_formatting.py
psql_chat/sql_utils.py
psql_chat-0.3.1.dist-info/licenses/LICENSE
psql_chat-0.3.1.dist-info/METADATA
psql_chat-0.3.1.dist-info/WHEEL
psql_chat-0.3.1.dist-info/entry_points.txt
psql_chat-0.3.1.dist-info/top_level.txt
psql_chat-0.3.1.dist-info/RECORD
