Metadata-Version: 2.4
Name: psql-chat
Version: 0.3.1
Summary: An AI-powered tool that can be called from inside psql to ask natural language questions about your PostgreSQL database with access to the database context and PostgreSQL documentation.
Author-email: Stefan Keller <stefan.keller@ost.ch>
Maintainer-email: Lars Herrmann <lars.herrmann@ost.ch>
License: PostgreSQL License (MIT-style)
Project-URL: Repository, https://gitlab.com/geometalab/psql-chat#
Keywords: sql,natural-language,postgresql,ai,llm,database,psql
Classifier: Programming Language :: Python :: 3
Classifier: Programming Language :: Python :: 3.11
Classifier: Programming Language :: Python :: 3.12
Classifier: Topic :: Database
Classifier: Topic :: Scientific/Engineering :: Artificial Intelligence
Requires-Python: >=3.11
License-File: LICENSE
Requires-Dist: openai>=1.0.0
Requires-Dist: psycopg2-binary>=2.9.0
Requires-Dist: python-dotenv>=0.19.0
Requires-Dist: rich>=13.0.0
Requires-Dist: typer>=0.20.0
Provides-Extra: dev
Requires-Dist: pytest>=7.0.0; extra == "dev"
Requires-Dist: black>=22.0.0; extra == "dev"
Requires-Dist: ruff>=0.1.0; extra == "dev"
Requires-Dist: mypy>=1.0.0; extra == "dev"
Requires-Dist: pre-commit>=3.0.0; extra == "dev"
Requires-Dist: isort>=5.13.2; extra == "dev"
Dynamic: license-file
